[
  {
    "q": "निम्नलिखित में से कौन 'निकट-दूर' (Proximo-distal) विकास का एक उदाहरण है?",
    "options": ["सिर से पैर तक विकास", "उंगलियों से पहले भुजाओं पर नियंत्रण", "सामान्य से विशिष्ट प्रतिक्रिया", "मानसिक से शारीरिक विकास"],
    "a": 1,
    "explanation": "निकट-दूर विकास का अर्थ है कि विकास शरीर के केंद्र से शुरू होता है और छोरों की ओर बढ़ता है।"
  },
  {
    "q": "'अव्यक्त अधिगम' (Latent Learning) की अवधारणा किसके द्वारा शुरू की गई थी?",
    "options": ["एडवर्ड टोलमैन", "बी.एफ. स्किनर", "इवान पावलोव", "अल्बर्ट बांडुरा"],
    "a": 0,
    "explanation": "टोलमैन ने सुझाव दिया कि सीखना तत्काल सुदृढीकरण के बिना हो सकता है और जरूरत पड़ने तक प्रदर्शित नहीं किया जा सकता है।"
  },
  {
    "q": "पियाजे के सिद्धांत की किस अवस्था में 'पारगमन तर्क' (Transductive Reasoning) होता है?",
    "options": ["संवेदी-गामक", "पूर्व-संक्रियात्मक", "मूर्त संक्रियात्मक", "औपचारिक संक्रियात्मक"],
    "a": 1,
    "explanation": "पूर्व-संक्रियात्मक अवस्था में, बच्चे अक्सर समय के करीब होने वाली दो विशिष्ट घटनाओं को जोड़ते हैं, भले ही वे संबंधित न हों।"
  },
  {
    "q": "कोहलबर्ग के अनुसार, 'सार्वभौमिक नैतिक सिद्धांत' नैतिकता का कौन सा चरण है?",
    "options": ["चरण 3", "चरण 4", "चरण 5", "चरण 6"],
    "a": 3,
    "explanation": "चरण 6 उच्चतम स्तर है जहाँ व्यक्ति स्वयं द्वारा चुने गए नैतिक सिद्धांतों का पालन करते हैं।"
  },
  {
    "q": "निम्नलिखित में से कौन सा एक 'सामाजिक' प्रेरक है?",
    "options": ["भूख", "प्यास", "उपलब्धि", "नींद"],
    "a": 2,
    "explanation": "उपलब्धि, संबद्धता और शक्ति को द्वितीयक या सामाजिक प्रेरक माना जाता है।"
  },
  {
    "q": "पढ़ना सिखाने की 'वर्णमाला विधि' को इस नाम से भी जाना जाता है:",
    "options": ["ध्वन्यात्मक विधि", "शब्द विधि", "अक्षर विधि", "वाक्य विधि"],
    "a": 2,
    "explanation": "अक्षर विधि में पहले अक्षरों के नाम और आकृतियों को सिखाना शामिल है।"
  },
  {
    "q": "मनोविज्ञान में 'प्रकार्यवादी' (Functionalism) के प्रस्तावक कौन हैं?",
    "options": ["विलियम जेम्स", "विल्हेम वुंड्ट", "सिग्मंड फ्रायड", "कर्ट लेविन"],
    "a": 0,
    "explanation": "विलियम जेम्स को प्रकार्यवाद का जनक माना जाता है, जो इस बात पर ध्यान केंद्रित करता है कि मन पर्यावरण के अनुकूल होने के लिए कैसे कार्य करता है।"
  },
  {
    "q": "एक शिक्षक एक छात्र को पहेली सुलझाने में मदद करने के लिए 'स्कैफोल्डिंग' का उपयोग करता है। यह सहायता है:",
    "options": ["स्थायी", "अस्थायी", "अनावश्यक", "विचलित करने वाली"],
    "a": 1,
    "explanation": "स्कैफोल्डिंग (वायगोत्स्की) अस्थायी सहायता है जो तब तक दी जाती है जब तक शिक्षार्थी स्वतंत्र रूप से कार्य नहीं कर सकता।"
  },
  {
    "q": "कौन सी IQ श्रेणी 'सीमावर्ती' (Borderline) बुद्धि का प्रतिनिधित्व करती है?",
    "options": ["110-119", "90-109", "70-79", "70 से नीचे"],
    "a": 2,
    "explanation": "70-79 को आमतौर पर सीमावर्ती के रूप में वर्गीकृत किया जाता है, जो बौद्धिक अक्षमता की सीमा से ठीक ऊपर है।"
  },
  {
    "q": "'सृजनात्मक' बच्चे की विशेषता आमतौर पर होती है:",
    "options": ["उच्च रटने वाली स्मृति", "अपसारी सोच", "अभिसारी सोच", "सख्त आज्ञाकारिता"],
    "a": 1,
    "explanation": "सृजनात्मकता अपसारी सोच (Divergent Thinking) से दृढ़ता से जुड़ी हुई है।"
  },
  {
    "q": "बचपन के विकास में 'खेल' की क्या भूमिका है?",
    "options": ["समय की बर्बादी", "केवल शारीरिक व्यायाम के लिए", "संज्ञानात्मक, सामाजिक और भावनात्मक विकास", "केवल खेल की तैयारी के लिए"],
    "a": 2,
    "explanation": "सामाजिक कौशल और समस्या समाधान सहित समग्र विकास के लिए खेल आवश्यक है।"
  },
  {
    "q": "'नायक' शब्द का स्त्रीलिंग रूप क्या है?",
    "options": ["नायकी", "नायिका", "नायिकी", "नायका"],
    "a": 1,
    "explanation": "नायक का स्त्रीलिंग नायिका होता है।"
  },
  {
    "q": "'तिरंगा' में कौन सा समास है?",
    "options": ["द्विगु", "द्वंद्व", "तत्पुरुष", "कर्मधारय"],
    "a": 0,
    "explanation": "तीन रंगों का समूह, प्रथम पद संख्यावाचक होने से द्विगु समास है।"
  },
  {
    "q": "'हर्ष' का विलोम शब्द है:",
    "options": ["खुशी", "विषाद", "दुख", "अप्रसन्नता"],
    "a": 1,
    "explanation": "हर्ष का विलोम शब्द 'विषाद' होता है।"
  },
  {
    "q": "'आँख का तारा' मुहावरे का अर्थ है:",
    "options": ["कम दिखना", "बहुत प्यारा होना", "आँख की बीमारी", "धोखा देना"],
    "a": 1,
    "explanation": "इसका अर्थ अत्यंत प्रिय होना है।"
  },
  {
    "q": "शुद्ध वर्तनी वाले शब्द का चयन करें:",
    "options": ["कवित्री", "कवयित्री", "कवियित्री", "कवयत्री"],
    "a": 1,
    "explanation": "सही वर्तनी 'कवयित्री' है।"
  },
  {
    "q": "'कमल' का पर्यायवाची शब्द नहीं है:",
    "options": ["पंकज", "जलज", "अम्बुद", "सरोज"],
    "a": 2,
    "explanation": "'अम्बुद' बादल का पर्यायवाची है।"
  },
  {
    "q": "क्रिया के मूल रूप को क्या कहते हैं?",
    "options": ["पद", "धातु", "शब्द", "उपसर्ग"],
    "a": 1,
    "explanation": "क्रिया के मूल रूप को 'धातु' कहा जाता है, जैसे 'पढ़' धातु से 'पढ़ना' बना।"
  },
  {
    "q": "'Knife' का सही बहुवचन रूप चुनें:",
    "options": ["Knifes", "Knive", "Knives", "Knifess"],
    "a": 2,
    "explanation": "-fe पर समाप्त होने वाले शब्द आमतौर पर बहुवचन में -ves में बदल जाते हैं।"
  },
  {
    "q": "'Abundant' के लिए पर्यायवाची चुनें:",
    "options": ["Scarce", "Plentiful", "Rare", "Minimal"],
    "a": 1,
    "explanation": "Abundant का अर्थ है बड़ी मात्रा में विद्यमान; प्रचुर (Plentiful)।"
  },
  {
    "q": "वाक्य में 'Preposition' पहचानें: 'The book is on the table.'",
    "options": ["The", "Book", "Is", "On"],
    "a": 3,
    "explanation": "'On' किताब और मेज के बीच संबंध दिखाता है।"
  },
  {
    "q": "'Psychology' शब्द में कौन सा अक्षर 'मौन' (Silent) है?",
    "options": ["s", "p", "y", "h"],
    "a": 1,
    "explanation": "Psychology के आरंभ में 'p' का उच्चारण नहीं किया जाता है।"
  },
  {
    "q": "सही क्वेश्चन टैग चुनें: 'She can drive, ________?'",
    "options": ["can she", "can't she", "does she", "doesn't she"],
    "a": 1,
    "explanation": "'can' के साथ एक सकारात्मक वाक्य नकारात्मक टैग 'can't she' लेता है।"
  },
  {
    "q": "वाक्य में 'Subject' क्या है: 'Barking dogs seldom bite.'?",
    "options": ["Barking", "Dogs", "Barking dogs", "Seldom bite"],
    "a": 2,
    "explanation": "संपूर्ण संज्ञा वाक्यांश 'Barking dogs' विषय है।"
  },
  {
    "q": "सही आर्टिकल के साथ रिक्त स्थान भरें: 'Copper is ________ useful metal.'",
    "options": ["a", "an", "the", "No article"],
    "a": 0,
    "explanation": "'Useful' एक 'y' व्यंजन ध्वनि से शुरू होता है, इसलिए 'a' का उपयोग किया जाता है।"
  },
  {
    "q": "मध्यकालीन भारत की पहली महिला शासिका कौन थी?",
    "options": ["चांद बीबी", "रजिया सुल्तान", "नूरजहाँ", "रानी रुद्रमा देवी"],
    "a": 1,
    "explanation": "रजिया सुल्तान (इल्तुतमिश की पुत्री) ने 1236-1240 तक दिल्ली सल्तनत पर शासन किया।"
  },
  {
    "q": "वायुमंडल की कौन सी परत रेडियो तरंगों को पृथ्वी पर वापस परावर्तित करती है?",
    "options": ["क्षोभमंडल", "समतापमंडल", "आयनमंडल", "मध्यमंडल"],
    "a": 2,
    "explanation": "आयनमंडल में आवेशित कण होते हैं जो रेडियो तरंगों को परावर्तित करते हैं।"
  },
  {
    "q": "सैन फ्रांसिस्को में 'गदर पार्टी' की स्थापना किसने की थी?",
    "options": ["लाला हरदयाल", "भगत सिंह", "वी.डी. सावरकर", "सोहन सिंह भकना"],
    "a": 0,
    "explanation": "लाला हरदयाल 1913 में गदर पार्टी के प्रमुख आयोजक थे।"
  },
  {
    "q": "'पाक जलडमरूमध्य' किन दो देशों के बीच स्थित है?",
    "options": ["भारत और पाकिस्तान", "भारत और श्रीलंका", "भारत और मालदीव", "भारत और म्यांमार"],
    "a": 1,
    "explanation": "पाक जलडमरूमध्य एक जल निकाय है जो तमिलनाडु (भारत) को श्रीलंका से अलग करता है।"
  },
  {
    "q": "'शोषण के विरुद्ध अधिकार' में किसका निषेध शामिल है?",
    "options": ["अस्पृश्यता", "मानव तस्करी और जबरन श्रम", "धार्मिक भेदभाव", "शीर्षक का उपयोग"],
    "a": 1,
    "explanation": "भारतीय संविधान के अनुच्छेद 23 और 24 तस्करी और बाल श्रम को प्रतिबंधित करते हैं।"
  },
  {
    "q": "प्रसिद्ध पुस्तक 'द स्पिरिट ऑफ लॉज' किसने लिखी थी?",
    "options": ["रूसो", "मोंटेस्क्यू", "वोल्टेयर", "जॉन लॉक"],
    "a": 1,
    "explanation": "मोंटेस्क्यू ने इस पुस्तक में शक्तियों के पृथक्करण का प्रस्ताव दिया था।"
  },
  {
    "q": "भारत के किस बंदरगाह को 'सभी बंदरगाहों का रत्न' कहा जाता है?",
    "options": ["कांडला", "विशाखापत्तनम", "मुंबई", "चेन्नई"],
    "a": 1,
    "explanation": "विशाखापत्तनम एक प्राकृतिक, स्थलपद्ध और सुरक्षित बंदरगाह है।"
  },
  {
    "q": "'कैबिनेट मिशन' किस वर्ष भारत आया था?",
    "options": ["1942", "1945", "1946", "1947"],
    "a": 2,
    "explanation": "सत्ता के हस्तांतरण पर चर्चा करने के लिए मिशन 1946 में आया था।"
  },
  {
    "q": "भारत में राज्य स्तर पर कानून बनाने के लिए कौन सा निकाय उत्तरदायी है?",
    "options": ["संसद", "राज्य विधानमंडल", "राज्यपाल", "सर्वोच्च न्यायालय"],
    "a": 1,
    "explanation": "विधानसभा (और विधान परिषद, जहाँ लागू हो) राज्य स्तर के कानून बनाती है।"
  },
  {
    "q": "'दक्कन का पठार' किस प्रकार की चट्टानों से बना था?",
    "options": ["अवसादी", "कायांतरित", "बेसाल्टिक आग्नेय", "ग्रेनाइट"],
    "a": 2,
    "explanation": "दक्कन ट्रैप का निर्माण ज्वालामुखीय उद्भेदन से हुआ था जिससे बेसाल्टिक मिट्टी बनी।"
  },
  {
    "q": "प्रारूप समिति के 'संवैधानिक सलाहकार' कौन थे?",
    "options": ["डॉ. बी.आर. अंबेडकर", "डॉ. राजेंद्र प्रसाद", "बी.एन. राव", "के.एम. मुंशी"],
    "a": 2,
    "explanation": "सर बेनेगल नरसिंह राव वह सलाहकार थे जिन्होंने प्रारंभिक मसौदा तैयार किया था।"
  },
  {
    "q": "कौन सा आंदोलन 'साइमन गो बैक' के नारे से संबंधित है?",
    "options": ["असहयोग आंदोलन", "सविनय अवज्ञा आंदोलन", "साइमन कमीशन विरोधी प्रदर्शन", "भारत छोड़ो आंदोलन"],
    "a": 2,
    "explanation": "1928 में विरोध प्रदर्शन हुए क्योंकि आयोग में कोई भारतीय सदस्य नहीं था।"
  },
  {
    "q": "भारत का 'सबसे ऊँचा जलप्रपात' कौन सा है?",
    "options": ["दूधसागर जलप्रपात", "जोग जलप्रपात", "कुंचिकल जलप्रपात", "नोहकलिकाई जलप्रपात"],
    "a": 2,
    "explanation": "कर्नाटक में कुंचिकल जलप्रपात वर्तमान में भारत में सबसे ऊँचा माना जाता है।"
  },
  {
    "q": "भारत का 'राष्ट्रपति' बनने के लिए न्यूनतम आयु क्या है?",
    "options": ["25 वर्ष", "30 वर्ष", "35 वर्ष", "40 वर्ष"],
    "a": 2,
    "explanation": "अनुच्छेद 58 न्यूनतम आयु आवश्यकता के रूप में 35 वर्ष निर्दिष्ट करता है।"
  },
  {
    "q": "सिंधु घाटी का 'लोथल' गोदीवाड़ा किस राज्य में स्थित है?",
    "options": ["राजस्थान", "पंजाब", "गुजरात", "हरियाणा"],
    "a": 2,
    "explanation": "लोथल आधुनिक गुजरात में हड़प्पा सभ्यता का एक प्रमुख बंदरगाह शहर था।"
  }
]
